zoomies/__init__.py
zoomies/kinematic_relation.py
zoomies/quick_jz.py
zoomies-0.0.1.dist-info/METADATA
zoomies-0.0.1.dist-info/WHEEL
zoomies-0.0.1.dist-info/licenses/LICENSE
zoomies-0.0.1.dist-info/RECORD
