Metadata-Version: 2.1
Name: zoomies
Version: 0.0.1
Summary: Age prediction tool woohoo
Project-URL: Homepage, https://github.com/ssagear/zoomies
Author-email: Sheila Sagear <ssagearastro@gmail.com>
License-File: LICENSE
Classifier: License :: OSI Approved :: MIT License
Classifier: Operating System :: OS Independent
Classifier: Programming Language :: Python :: 3
Requires-Python: >=3.7
